{
  "accentColor": "{{appsmith.theme.colors.primaryColor}}",
  "animateLoading": true,
  "autoFocus": false,
  "borderRadius": "{{appsmith.theme.borderRadius.appBorderRadius}}",
  "bottomRow": 27,
  "boxShadow": "none",
  "defaultText": "",
  "dynamicBindingPathList": [
    {
      "key": "accentColor"
    },
    {
      "key": "borderRadius"
    }
  ],
  "dynamicHeight": "FIXED",
  "dynamicTriggerPathList": [],
  "iconAlign": "left",
  "inputType": "PASSWORD",
  "isDisabled": false,
  "isLoading": false,
  "isRequired": false,
  "isVisible": true,
  "key": "1d538atk35",
  "label": "Senha",
  "labelAlignment": "left",
  "labelPosition": "Top",
  "labelStyle": "",
  "labelTextSize": "0.875rem",
  "labelWidth": 5,
  "leftColumn": 5,
  "maxDynamicHeight": 9000,
  "minDynamicHeight": 4,
  "minWidth": 450,
  "mobileBottomRow": 27,
  "mobileLeftColumn": 5,
  "mobileRightColumn": 25,
  "mobileTopRow": 20,
  "needsErrorInfo": false,
  "parentColumnSpace": 20.21875,
  "parentId": "0",
  "parentRowSpace": 10,
  "renderMode": "CANVAS",
  "resetOnSubmit": true,
  "responsiveBehavior": "fill",
  "rightColumn": 25,
  "shouldAllowAutofill": true,
  "showStepArrows": false,
  "topRow": 20,
  "type": "INPUT_WIDGET_V2",
  "version": 2,
  "widgetId": "xtojj7rr37",
  "widgetName": "hp_inp_senha"
}